allowed/__init__.py
allowed/__main__.py
allowed/allowed.py
allowed/ls_client.py
allowed/m269-24j.json
allowed/m269-25j.json
allowed/m269.json
allowed/tm112.json
allowed-1.5.5.dist-info/LICENCE.MD
allowed-1.5.5.dist-info/METADATA
allowed-1.5.5.dist-info/WHEEL
allowed-1.5.5.dist-info/entry_points.txt
allowed-1.5.5.dist-info/RECORD
