Metadata-Version: 2.3
Name: allowed
Version: 1.5.5
Summary: Check if a program only uses a subset of the Python language.
License: BSD-3-Clause
Keywords: education
Author: Michel Wermelinger
Author-email: michel.wermelinger@open.ac.uk
Requires-Python: >=3.10,<4.0
Classifier: Intended Audience :: Education
Classifier: License :: OSI Approved :: BSD License
Classifier: Operating System :: OS Independent
Classifier: Programming Language :: Python :: 3
Classifier: Programming Language :: Python :: 3.10
Classifier: Programming Language :: Python :: 3.11
Classifier: Programming Language :: Python :: 3.12
Classifier: Programming Language :: Python :: 3.13
Classifier: Topic :: Education
Requires-Dist: pyrefly (>=0.39.2,<0.40.0)
Project-URL: Changelog, https://github.com/dsa-ou/allowed/blob/main/CHANGELOG.md
Project-URL: Homepage, https://dsa-ou.github.io/allowed
Project-URL: Repository, https://github.com/dsa-ou/allowed
